trytond/modules/health_pediatrics/COPYING
trytond/modules/health_pediatrics/README.rst
trytond/modules/health_pediatrics/__init__.py
trytond/modules/health_pediatrics/data/gnuhealth_commands.xml
trytond/modules/health_pediatrics/health_pediatrics.py
trytond/modules/health_pediatrics/health_pediatrics_report.xml
trytond/modules/health_pediatrics/health_pediatrics_view.xml
trytond/modules/health_pediatrics/icons/baby_boy_sitting.svg
trytond/modules/health_pediatrics/locale/ar.po
trytond/modules/health_pediatrics/locale/de.po
trytond/modules/health_pediatrics/locale/el.po
trytond/modules/health_pediatrics/locale/eo.po
trytond/modules/health_pediatrics/locale/es.po
trytond/modules/health_pediatrics/locale/fr.po
trytond/modules/health_pediatrics/locale/health_pediatrics.pot
trytond/modules/health_pediatrics/locale/it_IT.po
trytond/modules/health_pediatrics/locale/ja_JP.po
trytond/modules/health_pediatrics/locale/ka.po
trytond/modules/health_pediatrics/locale/lo.po
trytond/modules/health_pediatrics/locale/pt_BR.po
trytond/modules/health_pediatrics/locale/sv.po
trytond/modules/health_pediatrics/locale/tr.po
trytond/modules/health_pediatrics/locale/uk.po
trytond/modules/health_pediatrics/locale/zh_CN.po
trytond/modules/health_pediatrics/pyproject.toml
trytond/modules/health_pediatrics/report/newborn_card.fodt
trytond/modules/health_pediatrics/security/access_rights.xml
trytond/modules/health_pediatrics/tests/__init__.py
trytond/modules/health_pediatrics/tests/test_health_pediatrics.py
trytond/modules/health_pediatrics/tryton.cfg
trytond/modules/health_pediatrics/view/gnuhealth_neonatal_apgar.xml
trytond/modules/health_pediatrics/view/gnuhealth_neonatal_apgar_tree.xml
trytond/modules/health_pediatrics/view/gnuhealth_newborn.xml
trytond/modules/health_pediatrics/view/gnuhealth_newborn_tree.xml
trytond/modules/health_pediatrics/view/gnuhealth_pediatric_symptoms_checklist.xml
trytond/modules/health_pediatrics/view/gnuhealth_pediatric_symptoms_checklist_tree.xml
gnuhealth_pediatrics-5.0.2.dist-info/METADATA
gnuhealth_pediatrics-5.0.2.dist-info/WHEEL
gnuhealth_pediatrics-5.0.2.dist-info/licenses/COPYING
gnuhealth_pediatrics-5.0.2.dist-info/RECORD
